{
  "version": "1.0.0",
  "lastScanned": 1774085382392,
  "projectRoot": "/home/matcry/Documents/EduKho-AI.",
  "techStack": {
    "languages": [
      {
        "name": "JavaScript/TypeScript",
        "version": null,
        "confidence": "high",
        "markers": [
          "package.json"
        ]
      },
      {
        "name": "PHP",
        "version": null,
        "confidence": "high",
        "markers": [
          "composer.json"
        ]
      }
    ],
    "frameworks": [
      {
        "name": "vite",
        "version": "5.4.2",
        "category": "build"
      }
    ],
    "packageManager": "composer",
    "runtime": null
  },
  "build": {
    "buildCommand": "npm run build",
    "testCommand": null,
    "lintCommand": null,
    "devCommand": "npm run dev",
    "scripts": {
      "dev": "vite",
      "build": "vite build"
    }
  },
  "conventions": {
    "namingStyle": null,
    "importStyle": null,
    "testPattern": null,
    "fileOrganization": null
  },
  "structure": {
    "isMonorepo": false,
    "workspaces": [],
    "mainDirectories": [
      "app",
      "public",
      "scripts",
      "tests"
    ],
    "gitBranches": {
      "defaultBranch": "main",
      "branchingStrategy": null
    }
  },
  "customNotes": [],
  "directoryMap": {
    "app": {
      "path": "app",
      "purpose": "Application code",
      "fileCount": 0,
      "lastAccessed": 1774085382383,
      "keyFiles": []
    },
    "bootstrap": {
      "path": "bootstrap",
      "purpose": null,
      "fileCount": 2,
      "lastAccessed": 1774085382383,
      "keyFiles": [
        "app.php",
        "providers.php"
      ]
    },
    "config": {
      "path": "config",
      "purpose": "Configuration files",
      "fileCount": 8,
      "lastAccessed": 1774085382389,
      "keyFiles": [
        "app.php",
        "auth.php",
        "cache.php",
        "database.php",
        "queue.php"
      ]
    },
    "database": {
      "path": "database",
      "purpose": null,
      "fileCount": 0,
      "lastAccessed": 1774085382389,
      "keyFiles": []
    },
    "public": {
      "path": "public",
      "purpose": "Public files",
      "fileCount": 2,
      "lastAccessed": 1774085382390,
      "keyFiles": [
        "index.php"
      ]
    },
    "resources": {
      "path": "resources",
      "purpose": null,
      "fileCount": 0,
      "lastAccessed": 1774085382390,
      "keyFiles": []
    },
    "routes": {
      "path": "routes",
      "purpose": "Route handlers",
      "fileCount": 3,
      "lastAccessed": 1774085382391,
      "keyFiles": [
        "api.php",
        "console.php",
        "web.php"
      ]
    },
    "scripts": {
      "path": "scripts",
      "purpose": "Build/utility scripts",
      "fileCount": 3,
      "lastAccessed": 1774085382391,
      "keyFiles": [
        "dev-doctor.sh",
        "dev-up.sh",
        "ensure-local-files.sh"
      ]
    },
    "storage": {
      "path": "storage",
      "purpose": null,
      "fileCount": 0,
      "lastAccessed": 1774085382391,
      "keyFiles": []
    },
    "tests": {
      "path": "tests",
      "purpose": "Test files",
      "fileCount": 1,
      "lastAccessed": 1774085382391,
      "keyFiles": [
        "TestCase.php"
      ]
    },
    "vendor": {
      "path": "vendor",
      "purpose": "Third-party code",
      "fileCount": 1,
      "lastAccessed": 1774085382391,
      "keyFiles": [
        "autoload.php"
      ]
    },
    "app/Models": {
      "path": "app/Models",
      "purpose": "Data models",
      "fileCount": 18,
      "lastAccessed": 1774085382391,
      "keyFiles": [
        "ActivityLog.php",
        "AiChatLog.php",
        "BorrowDetail.php"
      ]
    },
    "app/Services": {
      "path": "app/Services",
      "purpose": "Business logic services",
      "fileCount": 3,
      "lastAccessed": 1774085382391,
      "keyFiles": [
        "ActivityLogger.php",
        "DepreciationService.php",
        "TwoFactorService.php"
      ]
    },
    "database/migrations": {
      "path": "database/migrations",
      "purpose": "Database migrations",
      "fileCount": 25,
      "lastAccessed": 1774085382392,
      "keyFiles": [
        "2025_01_01_000001_create_departments_table.php",
        "2025_01_01_000002_create_users_table.php",
        "2025_01_01_000003_create_rooms_table.php"
      ]
    },
    "public/build": {
      "path": "public/build",
      "purpose": "Build output",
      "fileCount": 1,
      "lastAccessed": 1774085382392,
      "keyFiles": [
        "manifest.json"
      ]
    },
    "resources/views": {
      "path": "resources/views",
      "purpose": "View templates",
      "fileCount": 0,
      "lastAccessed": 1774085382392,
      "keyFiles": []
    },
    "storage/app": {
      "path": "storage/app",
      "purpose": "Application code",
      "fileCount": 0,
      "lastAccessed": 1774085382392,
      "keyFiles": []
    },
    "vendor/bin": {
      "path": "vendor/bin",
      "purpose": "Executable scripts",
      "fileCount": 5,
      "lastAccessed": 1774085382392,
      "keyFiles": [
        "carbon",
        "patch-type-declarations",
        "php-parse"
      ]
    }
  },
  "hotPaths": [
    {
      "path": "app/Providers/AppServiceProvider.php",
      "accessCount": 3,
      "lastAccessed": 1774086335961,
      "type": "file"
    },
    {
      "path": "bootstrap/app.php",
      "accessCount": 3,
      "lastAccessed": 1774086346794,
      "type": "file"
    },
    {
      "path": ".env",
      "accessCount": 2,
      "lastAccessed": 1774086340268,
      "type": "file"
    },
    {
      "path": "app/Services/AI/GeminiService.php",
      "accessCount": 1,
      "lastAccessed": 1774085549594,
      "type": "file"
    },
    {
      "path": "routes/api.php",
      "accessCount": 1,
      "lastAccessed": 1774085816324,
      "type": "file"
    },
    {
      "path": "config/services.php",
      "accessCount": 1,
      "lastAccessed": 1774085817213,
      "type": "file"
    },
    {
      "path": "routes/web.php",
      "accessCount": 1,
      "lastAccessed": 1774085817267,
      "type": "file"
    },
    {
      "path": "resources/views/ai/chat.blade.php",
      "accessCount": 1,
      "lastAccessed": 1774085817491,
      "type": "file"
    },
    {
      "path": "config/sanctum.php",
      "accessCount": 1,
      "lastAccessed": 1774085823485,
      "type": "file"
    },
    {
      "path": "app/Http/Controllers/AiChatController.php",
      "accessCount": 1,
      "lastAccessed": 1774085827433,
      "type": "file"
    },
    {
      "path": "app/Services/AI/AiServiceManager.php",
      "accessCount": 1,
      "lastAccessed": 1774085832660,
      "type": "file"
    },
    {
      "path": "app/Services/AI/GroqService.php",
      "accessCount": 1,
      "lastAccessed": 1774086305521,
      "type": "file"
    }
  ],
  "userDirectives": []
}